py_stringsimjoin/__init__.py
py_stringsimjoin/datasets/__init__.py
py_stringsimjoin/datasets/base.py
py_stringsimjoin/datasets/data/books_table_A.csv.gz
py_stringsimjoin/datasets/data/books_table_B.csv.gz
py_stringsimjoin/datasets/data/person_table_A.csv
py_stringsimjoin/datasets/data/person_table_B.csv
py_stringsimjoin/filter/__init__.py
py_stringsimjoin/filter/filter.py
py_stringsimjoin/filter/filter_utils.py
py_stringsimjoin/filter/overlap_filter.py
py_stringsimjoin/filter/position_filter.py
py_stringsimjoin/filter/prefix_filter.py
py_stringsimjoin/filter/size_filter.py
py_stringsimjoin/filter/suffix_filter.py
py_stringsimjoin/index/__init__.py
py_stringsimjoin/index/index.py
py_stringsimjoin/index/inverted_index.py
py_stringsimjoin/index/inverted_index_cy.cpp
py_stringsimjoin/index/inverted_index_cy.cpython-311-darwin.so
py_stringsimjoin/index/inverted_index_cy.pyx
py_stringsimjoin/index/position_index.py
py_stringsimjoin/index/position_index_cy.cpp
py_stringsimjoin/index/position_index_cy.cpython-311-darwin.so
py_stringsimjoin/index/position_index_cy.pyx
py_stringsimjoin/index/prefix_index.py
py_stringsimjoin/index/size_index.py
py_stringsimjoin/join/__init__.py
py_stringsimjoin/join/cosine_join.py
py_stringsimjoin/join/cosine_join_cy.cpp
py_stringsimjoin/join/cosine_join_cy.cpython-311-darwin.so
py_stringsimjoin/join/cosine_join_cy.pyx
py_stringsimjoin/join/cosine_join_py.py
py_stringsimjoin/join/dice_join.py
py_stringsimjoin/join/dice_join_cy.cpp
py_stringsimjoin/join/dice_join_cy.cpython-311-darwin.so
py_stringsimjoin/join/dice_join_cy.pyx
py_stringsimjoin/join/dice_join_py.py
py_stringsimjoin/join/disk_edit_distance_join.py
py_stringsimjoin/join/disk_edit_distance_join_cy.cpp
py_stringsimjoin/join/disk_edit_distance_join_cy.cpython-311-darwin.so
py_stringsimjoin/join/disk_edit_distance_join_cy.pyx
py_stringsimjoin/join/edit_distance_join.py
py_stringsimjoin/join/edit_distance_join_cy.cpp
py_stringsimjoin/join/edit_distance_join_cy.cpython-311-darwin.so
py_stringsimjoin_temp-0.3.3.dist-info/LICENSE
py_stringsimjoin_temp-0.3.3.dist-info/METADATA
py_stringsimjoin_temp-0.3.3.dist-info/WHEEL
py_stringsimjoin_temp-0.3.3.dist-info/top_level.txt
py_stringsimjoin_temp-0.3.3.dist-info/RECORD
