Metadata-Version: 2.1
Name: py-stringsimjoin-temp
Version: 0.3.3
Summary: Python library for performing string similarity joins.
Home-page: https://sites.google.com/site/anhaidgroup/projects/magellan/py_stringsimjoin
Author: UW Magellan Team
Author-email: uwmagellan@gmail.com
License: BSD
Classifier: Development Status :: 4 - Beta
Classifier: Environment :: Console
Classifier: Intended Audience :: Developers
Classifier: Intended Audience :: Science/Research
Classifier: Intended Audience :: Education
Classifier: License :: OSI Approved :: BSD License
Classifier: Operating System :: POSIX
Classifier: Operating System :: Unix
Classifier: Operating System :: MacOS
Classifier: Operating System :: Microsoft :: Windows
Classifier: Programming Language :: Python
Classifier: Programming Language :: Python :: 3
Classifier: Programming Language :: Python :: 3.7
Classifier: Programming Language :: Python :: 3.8
Classifier: Programming Language :: Python :: 3.9
Classifier: Programming Language :: Python :: 3.10
Classifier: Programming Language :: Python :: 3.11
Classifier: Topic :: Scientific/Engineering
Classifier: Topic :: Utilities
Classifier: Topic :: Software Development :: Libraries
License-File: LICENSE
Requires-Dist: joblib
Requires-Dist: pandas (>=0.16.0)
Requires-Dist: PyPrind (>=2.9.3)
Requires-Dist: py-stringmatching (>=0.2.1)
Requires-Dist: six
